pyloopmessage/__init__.py
pyloopmessage/client.py
pyloopmessage/enums.py
pyloopmessage/exceptions.py
pyloopmessage/models.py
pyloopmessage/py.typed
pyloopmessage/utils.py
pyloopmessage/beta/__init__.py
pyloopmessage/beta/client.py
pyloopmessage/beta/enums.py
pyloopmessage/beta/models.py
pyloopmessage-0.3.1.dist-info/licenses/LICENSE
pyloopmessage-0.3.1.dist-info/METADATA
pyloopmessage-0.3.1.dist-info/WHEEL
pyloopmessage-0.3.1.dist-info/top_level.txt
pyloopmessage-0.3.1.dist-info/RECORD
